countingworkspace/__init__.py
countingworkspace/countingworkspace.py
countingworkspace/examples.py
countingworkspace/utils.py
tests/__init__.py
tests/bug.py
tests/test_all.py
countingworkspace-0.2.2.dist-info/METADATA
countingworkspace-0.2.2.dist-info/WHEEL
countingworkspace-0.2.2.dist-info/top_level.txt
countingworkspace-0.2.2.dist-info/RECORD
