Metadata-Version: 2.1
Name: countingworkspace
Version: 0.2.2
Summary: Simple builder for counting experiment RooFit workspace
Home-page: https://github.com/wiso/countingworkspace
Author: Ruggero Turra
Author-email: ruggero.turra@cern.ch
License: UNKNOWN
Platform: UNKNOWN
Classifier: Programming Language :: Python :: 3
Classifier: Programming Language :: Python :: 2
Classifier: Development Status :: 3 - Alpha
Classifier: Operating System :: OS Independent
Requires-Dist: numpy
Requires-Dist: scipy
